bnltk/__init__.py
bnltk/bnltk_downloads/__init__.py
bnltk/bnltk_downloads/file_downloader.py
bnltk/pos_tagger/__init__.py
bnltk/pos_tagger/bn_pos_tagger.py
bnltk/pos_tagger/trained_model.py
bnltk/stemmer/__init__.py
bnltk/stemmer/stemmer_builder.py
bnltk/stemmer/test_stemmer_builder.py
bnltk/tests/__init__.py
bnltk/tests/test_stemmer_builder.py
bnltk/tokenize/__init__.py
bnltk/tokenize/bn_word_tokenizers.py
bnltk_downloads/__init__.py
bnltk_downloads/file_downloader.py
pos_tagger/__init__.py
pos_tagger/bn_pos_tagger.py
pos_tagger/trained_model.py
stemmer/__init__.py
stemmer/stemmer_builder.py
stemmer/test_stemmer_builder.py
tests/__init__.py
tests/test_stemmer_builder.py
tokenize/__init__.py
tokenize/bn_word_tokenizers.py
bnltk_revamped-0.1.2.dist-info/LICENSE
bnltk_revamped-0.1.2.dist-info/METADATA
bnltk_revamped-0.1.2.dist-info/WHEEL
bnltk_revamped-0.1.2.dist-info/top_level.txt
bnltk_revamped-0.1.2.dist-info/RECORD
